setup.cfg
setup.py
vvl/Generaldistribution.py
vvl/__init__.py
vvl/vvl.py
vvl.egg-info/PKG-INFO
vvl.egg-info/SOURCES.txt
vvl.egg-info/dependency_links.txt
vvl.egg-info/not-zip-safe
vvl.egg-info/top_level.txt