Metadata-Version: 2.1
Name: vvl
Version: 0.0
Summary: Gaussian and Binomial distributions
Author-email: 89242194144@mail.ru
